LICENSE
MANIFEST.in
README.rst
check.py
requirements.txt
setup.cfg
setup.py
tox.ini
src/justbases_string/__init__.py
src/justbases_string/_approx.py
src/justbases_string/_config.py
src/justbases_string/_errors.py
src/justbases_string/_string.py
src/justbases_string/_version.py
src/justbases_string.egg-info/PKG-INFO
src/justbases_string.egg-info/SOURCES.txt
src/justbases_string.egg-info/dependency_links.txt
src/justbases_string.egg-info/requires.txt
src/justbases_string.egg-info/top_level.txt
tests/__init__.py
tests/_utils.py
tests/test_approx_display.py
tests/test_string.py